{
  "_fv": 34,
  "_type": "recipe",
  "definition": {
    "recipeType": "Crafting",
    "xpReward": 0.0,
    "cookingTime": 200,
    "recipeRetstackSize": 2,
    "group": "",
    "recipeShapeless": false,
    "recipeSlots": [
      {
        "value": "CUSTOM:TadaniteCrystal"
      },
      {
        "value": "Items.DIAMOND"
      },
      {
        "value": "CUSTOM:TadaniteCrystal"
      },
      {
        "value": "CUSTOM:ObsidifiedBlazeRod"
      },
      {
        "value": "CUSTOM:TadaniteBlock"
      },
      {
        "value": "CUSTOM:ObsidifiedBlazeRod"
      },
      {
        "value": "CUSTOM:TadaniteCrystal"
      },
      {
        "value": "Items.DIAMOND"
      },
      {
        "value": "CUSTOM:TadaniteCrystal"
      }
    ],
    "recipeReturnStack": {
      "value": "CUSTOM:TadaniteDiamond"
    },
    "name": "tadanite_diamond_r",
    "namespace": "mod"
  }
}